{
  "format_version": "1.0",
  "format_description": "Indexed Pixel Editor Palette File",
  "source": {
    "cgram_file": "/mnt/c/CustomScripts/KirbyMax/workshop/exhal-master/Cave.SnesCgRam.dmp",
    "palette_index": 12,
    "extraction_tool": "extract_palette_for_editor.py"
  },
  "palette": {
    "name": "CGRAM Palette 12",
    "colors": [
      [
        0,
        0,
        0
      ],
      [
        248,
        248,
        248
      ],
      [
        184,
        248,
        248
      ],
      [
        248,
        152,
        0
      ],
      [
        248,
        88,
        0
      ],
      [
        152,
        32,
        56
      ],
      [
        40,
        56,
        128
      ],
      [
        168,
        160,
        176
      ],
      [
        120,
        112,
        136
      ],
      [
        80,
        72,
        88
      ],
      [
        32,
        32,
        48
      ],
      [
        248,
        248,
        104
      ],
      [
        248,
        152,
        0
      ],
      [
        248,
        88,
        0
      ],
      [
        0,
        48,
        248
      ],
      [
        0,
        0,
        0
      ]
    ],
    "color_count": 16,
    "format": "RGB888"
  },
  "usage_hints": {
    "transparent_index": 0,
    "typical_use": "sprite",
    "kirby_palette": false
  },
  "editor_compatibility": {
    "indexed_pixel_editor": true,
    "supports_grayscale_mode": true,
    "auto_loadable": true
  }
}